hatch_demo/__init__.py
hatch_demo/cosine.py
hatch_demo/sine.py
hatch_demo/plot/__init__.py
hatch_demo/plot/bar.py
hatch_demo/plot/graph.py
hatch_demo_kaparoo-0.3.0.dist-info/METADATA
hatch_demo_kaparoo-0.3.0.dist-info/WHEEL
hatch_demo_kaparoo-0.3.0.dist-info/licenses/LICENSE.txt
hatch_demo_kaparoo-0.3.0.dist-info/RECORD
